Metadata-Version: 1.2
Name: hookery
Version: 5.0.1
Summary: Trivial, primitive, naive, and optimistic hooks in Python 3.6+
Home-page: https://github.com/jbasko/hookery
Author: Jazeps Basko
Author-email: jazeps.basko@gmail.com
Maintainer: Jazeps Basko
Maintainer-email: jazeps.basko@gmail.com
License: MIT
Platform: UNKNOWN
Classifier: Development Status :: 3 - Alpha
Classifier: Intended Audience :: Developers
Classifier: Programming Language :: Python
Classifier: Programming Language :: Python :: 3
Classifier: Programming Language :: Python :: 3.6
Classifier: Programming Language :: Python :: 3.7
Classifier: License :: OSI Approved :: MIT License
